intent_detection/__init__.py
intent_detection/cli.py
intent_detection/config.py
intent_detection/lang_detect.py
intent_detection/pipeline.py
intent_detection/pseudoppl.py
intent_detection/toxicity.py
intent_detection/utils.py
intent_detection-0.1.2.dist-info/METADATA
intent_detection-0.1.2.dist-info/WHEEL
intent_detection-0.1.2.dist-info/entry_points.txt
intent_detection-0.1.2.dist-info/licenses/LICENSE
intent_detection-0.1.2.dist-info/RECORD
